[
  {
    "id": 1,
    "word": "kat",
    "theme": "korte-woorden",
    "difficulty": "easy",
    "audio_file": "kat.mp3",
    "visual_explanation": {
      "rule": "Het woord 'kat' schrijf je zoals het klinkt: k-a-t.",
      "examples": [
        "katten",
        "katje",
        "poes"
      ],
      "tip": "Dit is een eenvoudig woord met korte klanken."
    }
  },
  {
    "id": 2,
    "word": "boom",
    "theme": "woorden-met-oo",
    "difficulty": "easy",
    "audio_file": "boom.mp3",
    "visual_explanation": {
      "rule": "Het woord 'boom' schrijf je met 'oo' omdat de 'o' lang klinkt.",
      "examples": [
        "bomen",
        "boompje",
        "dennenboom"
      ],
      "tip": "Lange 'o' = 'oo'. Zeg het langzaam: booom."
    }
  },
  {
    "id": 3,
    "word": "huis",
    "theme": "woorden-met-ui",
    "difficulty": "easy",
    "audio_file": "huis.mp3",
    "visual_explanation": {
      "rule": "Het woord 'huis' schrijf je met 'ui'.",
      "examples": [
        "huizen",
        "huisje",
        "boomhut"
      ],
      "tip": "De 'ui' klinkt als 'ow-i'."
    }
  },
  {
    "id": 4,
    "word": "rood",
    "theme": "kleuren",
    "difficulty": "easy",
    "audio_file": "rood.mp3",
    "visual_explanation": {
      "rule": "Het woord 'rood' schrijf je met 'oo' en eindigt op 'd'.",
      "examples": [
        "rode",
        "roder",
        "roodst"
      ],
      "tip": "Let op de dubbele 'o' en de 'd' aan het eind!"
    }
  },
  {
    "id": 5,
    "word": "bloem",
    "theme": "natuur",
    "difficulty": "medium",
    "audio_file": "bloem.mp3",
    "visual_explanation": {
      "rule": "Het woord 'bloem' schrijf je met 'oe'.",
      "examples": [
        "bloemen",
        "bloempje",
        "tulp"
      ],
      "tip": "De 'oe' klinkt als 'oe'. Probeer: bl-oe-m."
    }
  },
  {
    "id": 6,
    "word": "maan",
    "theme": "natuur",
    "difficulty": "easy",
    "audio_file": "maan.mp3",
    "visual_explanation": {
      "rule": "Het woord 'maan' schrijf je met 'aa' omdat de 'a' lang klinkt.",
      "examples": [
        "manen",
        "maantje",
        "volle maan"
      ],
      "tip": "Lange 'a' = 'aa'. Zeg het langzaam: maaan."
    }
  },
  {
    "id": 7,
    "word": "been",
    "theme": "lichaam",
    "difficulty": "easy",
    "audio_file": "been.mp3",
    "visual_explanation": {
      "rule": "Het woord 'been' schrijf je met 'ee' omdat de 'e' lang klinkt.",
      "examples": [
        "benen",
        "beentje",
        "arm"
      ],
      "tip": "Lange 'e' = 'ee'. Probeer: beeen."
    }
  },
  {
    "id": 8,
    "word": "deur",
    "theme": "huis",
    "difficulty": "medium",
    "audio_file": "deur.mp3",
    "visual_explanation": {
      "rule": "Het woord 'deur' schrijf je met 'eu'.",
      "examples": [
        "deuren",
        "deurtje",
        "voordeur"
      ],
      "tip": "De 'eu' klinkt als 'uh'. Let op de spelling!"
    }
  },
  {
    "id": 9,
    "word": "bal",
    "theme": "speelgoed",
    "difficulty": "easy",
    "audio_file": "bal.mp3",
    "visual_explanation": {
      "rule": "Het woord 'bal' schrijf je zoals het klinkt: b-a-l.",
      "examples": [
        "ballen",
        "balletje",
        "voetbal"
      ],
      "tip": "Een eenvoudig woord met een korte 'a'."
    }
  },
  {
    "id": 10,
    "word": "paard",
    "theme": "dieren",
    "difficulty": "medium",
    "audio_file": "paard.mp3",
    "visual_explanation": {
      "rule": "Het woord 'paard' schrijf je met 'aa' en eindigt op 'rd'.",
      "examples": [
        "paarden",
        "paardje",
        "pony"
      ],
      "tip": "Let op: 'aa' voor de lange 'a' en 'rd' aan het eind!"
    }
  }
]
